bulk_file_organizer-0.1.2.dist-info/licenses/LICENSE
bulk_organizer/__init__.py
bulk_organizer/cli.py
bulk_organizer/mapper.py
bulk_organizer/organizer.py
bulk_organizer/scanner.py
bulk_organizer/utils.py
bulk_file_organizer-0.1.2.dist-info/METADATA
bulk_file_organizer-0.1.2.dist-info/WHEEL
bulk_file_organizer-0.1.2.dist-info/entry_points.txt
bulk_file_organizer-0.1.2.dist-info/top_level.txt
bulk_file_organizer-0.1.2.dist-info/RECORD
