Metadata-Version: 2.4
Name: bulk-file-organizer
Version: 0.1.2
Summary: A colorful CLI tool that organizes files into categorized folders based on file extensions.
Author-email: Shravan Bobade <shravan.bobade.tech@gmail.com>
License-Expression: MIT
Project-URL: Homepage, https://github.com/Shravan250/bulk-file-organizer
Project-URL: Bug Tracker, https://github.com/Shravan250/bulk-file-organizer/issues
Requires-Python: >=3.10
License-File: LICENSE
Requires-Dist: rich>=13.0.0
Provides-Extra: dev
Requires-Dist: pytest; extra == "dev"
Requires-Dist: ruff; extra == "dev"
Requires-Dist: black; extra == "dev"
Dynamic: license-file
